{
    "meta": {
        "current_page": 1,
        "first_page_url": "https://www.robotevents.com/api/v2/teams/167565/matches?page=1",
        "from": 1,
        "last_page": 1,
        "last_page_url": "https://www.robotevents.com/api/v2/teams/167565/matches?page=1",
        "next_page_url": null,
        "path": "https://www.robotevents.com/api/v2/teams/167565/matches",
        "per_page": 50,
        "prev_page_url": null,
        "to": 9,
        "total": 9
    },
    "data": [
        {
            "id": 107549683,
            "event": {
                "id": 57770,
                "name": "SCTCC VEX U Regional Qualifying Tournament in Minnesota: VEX U Robotics Competition",
                "code": "RE-VURC-24-7770"
            },
            "division": {
                "id": 1,
                "name": "MN VEX U",
                "code": null
            },
            "round": 2,
            "instance": 1,
            "matchnum": 5,
            "scheduled": "2025-02-27T15:13:20-05:00",
            "started": "2025-02-27T15:53:24-05:00",
            "field": "Park Industries",
            "scored": false,
            "name": "Qualifier #5",
            "alliances": [
                {
                    "color": "blue",
                    "score": 47,
                    "teams": [
                        {
                            "team": {
                                "id": 75787,
                                "name": "MINES",
                                "code": null
                            },
                            "sitting": false
                        }
                    ]
                },
                {
                    "color": "red",
                    "score": 8,
                    "teams": [
                        {
                            "team": {
                                "id": 167565,
                                "name": "UND",
                                "code": null
                            },
                            "sitting": false
                        }
                    ]
                }
            ],
            "updated_at": "2025-02-27T20:08:49-05:00"
        },
        {
            "id": 107549686,
            "event": {
                "id": 57770,
                "name": "SCTCC VEX U Regional Qualifying Tournament in Minnesota: VEX U Robotics Competition",
                "code": "RE-VURC-24-7770"
            },
            "division": {
                "id": 1,
                "name": "MN VEX U",
                "code": null
            },
            "round": 2,
            "instance": 1,
            "matchnum": 8,
            "scheduled": "2025-02-27T15:23:20-05:00",
            "started": "2025-02-27T16:11:22-05:00",
            "field": "Park Industries",
            "scored": false,
            "name": "Qualifier #8",
            "alliances": [
                {
                    "color": "blue",
                    "score": 39,
                    "teams": [
                        {
                            "team": {
                                "id": 157098,
                                "name": "JACKS",
                                "code": null
                            },
                            "sitting": false
                        }
                    ]
                },
                {
                    "color": "red",
                    "score": 11,
                    "teams": [
                        {
                            "team": {
                                "id": 167565,
                                "name": "UND",
                                "code": null
                            },
                            "sitting": false
                        }
                    ]
                }
            ],
            "updated_at": "2025-02-27T20:08:49-05:00"
        },
        {
            "id": 107549689,
            "event": {
                "id": 57770,
                "name": "SCTCC VEX U Regional Qualifying Tournament in Minnesota: VEX U Robotics Competition",
                "code": "RE-VURC-24-7770"
            },
            "division": {
                "id": 1,
                "name": "MN VEX U",
                "code": null
            },
            "round": 2,
            "instance": 1,
            "matchnum": 11,
            "scheduled": "2025-02-27T15:33:20-05:00",
            "started": "2025-02-27T16:26:09-05:00",
            "field": "Park Industries",
            "scored": false,
            "name": "Qualifier #11",
            "alliances": [
                {
                    "color": "blue",
                    "score": 2,
                    "teams": [
                        {
                            "team": {
                                "id": 167565,
                                "name": "UND",
                                "code": null
                            },
                            "sitting": false
                        }
                    ]
                },
                {
                    "color": "red",
                    "score": 36,
                    "teams": [
                        {
                            "team": {
                                "id": 162290,
                                "name": "DEVIL5",
                                "code": null
                            },
                            "sitting": false
                        }
                    ]
                }
            ],
            "updated_at": "2025-02-27T20:08:49-05:00"
        },
        {
            "id": 107549696,
            "event": {
                "id": 57770,
                "name": "SCTCC VEX U Regional Qualifying Tournament in Minnesota: VEX U Robotics Competition",
                "code": "RE-VURC-24-7770"
            },
            "division": {
                "id": 1,
                "name": "MN VEX U",
                "code": null
            },
            "round": 2,
            "instance": 1,
            "matchnum": 18,
            "scheduled": "2025-02-27T15:56:40-05:00",
            "started": "2025-02-27T17:05:00-05:00",
            "field": "UND",
            "scored": false,
            "name": "Qualifier #18",
            "alliances": [
                {
                    "color": "blue",
                    "score": 3,
                    "teams": [
                        {
                            "team": {
                                "id": 167565,
                                "name": "UND",
                                "code": null
                            },
                            "sitting": false
                        }
                    ]
                },
                {
                    "color": "red",
                    "score": 51,
                    "teams": [
                        {
                            "team": {
                                "id": 63958,
                                "name": "UMN",
                                "code": null
                            },
                            "sitting": false
                        }
                    ]
                }
            ],
            "updated_at": "2025-02-27T20:08:49-05:00"
        },
        {
            "id": 107549701,
            "event": {
                "id": 57770,
                "name": "SCTCC VEX U Regional Qualifying Tournament in Minnesota: VEX U Robotics Competition",
                "code": "RE-VURC-24-7770"
            },
            "division": {
                "id": 1,
                "name": "MN VEX U",
                "code": null
            },
            "round": 2,
            "instance": 1,
            "matchnum": 23,
            "scheduled": "2025-02-27T16:13:20-05:00",
            "started": "2025-02-27T17:25:46-05:00",
            "field": "Park Industries",
            "scored": false,
            "name": "Qualifier #23",
            "alliances": [
                {
                    "color": "blue",
                    "score": 0,
                    "teams": [
                        {
                            "team": {
                                "id": 162386,
                                "name": "CYBER5",
                                "code": null
                            },
                            "sitting": false
                        }
                    ]
                },
                {
                    "color": "red",
                    "score": 6,
                    "teams": [
                        {
                            "team": {
                                "id": 167565,
                                "name": "UND",
                                "code": null
                            },
                            "sitting": false
                        }
                    ]
                }
            ],
            "updated_at": "2025-02-27T20:08:49-05:00"
        },
        {
            "id": 107549703,
            "event": {
                "id": 57770,
                "name": "SCTCC VEX U Regional Qualifying Tournament in Minnesota: VEX U Robotics Competition",
                "code": "RE-VURC-24-7770"
            },
            "division": {
                "id": 1,
                "name": "MN VEX U",
                "code": null
            },
            "round": 2,
            "instance": 1,
            "matchnum": 25,
            "scheduled": "2025-02-27T16:20:00-05:00",
            "started": "2025-02-27T17:32:52-05:00",
            "field": "Coldspring",
            "scored": false,
            "name": "Qualifier #25",
            "alliances": [
                {
                    "color": "blue",
                    "score": 22,
                    "teams": [
                        {
                            "team": {
                                "id": 59198,
                                "name": "ESR1",
                                "code": null
                            },
                            "sitting": false
                        }
                    ]
                },
                {
                    "color": "red",
                    "score": 4,
                    "teams": [
                        {
                            "team": {
                                "id": 167565,
                                "name": "UND",
                                "code": null
                            },
                            "sitting": false
                        }
                    ]
                }
            ],
            "updated_at": "2025-02-27T20:08:49-05:00"
        },
        {
            "id": 107549709,
            "event": {
                "id": 57770,
                "name": "SCTCC VEX U Regional Qualifying Tournament in Minnesota: VEX U Robotics Competition",
                "code": "RE-VURC-24-7770"
            },
            "division": {
                "id": 1,
                "name": "MN VEX U",
                "code": null
            },
            "round": 2,
            "instance": 1,
            "matchnum": 31,
            "scheduled": "2025-02-27T16:40:00-05:00",
            "started": null,
            "field": "Coldspring",
            "scored": false,
            "name": "Qualifier #31",
            "alliances": [
                {
                    "color": "blue",
                    "score": 0,
                    "teams": [
                        {
                            "team": {
                                "id": 167565,
                                "name": "UND",
                                "code": null
                            },
                            "sitting": false
                        }
                    ]
                },
                {
                    "color": "red",
                    "score": 0,
                    "teams": [
                        {
                            "team": {
                                "id": 99253,
                                "name": "BISON1",
                                "code": null
                            },
                            "sitting": false
                        }
                    ]
                }
            ],
            "updated_at": "2025-02-27T20:08:49-05:00"
        },
        {
            "id": 107549712,
            "event": {
                "id": 57770,
                "name": "SCTCC VEX U Regional Qualifying Tournament in Minnesota: VEX U Robotics Competition",
                "code": "RE-VURC-24-7770"
            },
            "division": {
                "id": 1,
                "name": "MN VEX U",
                "code": null
            },
            "round": 2,
            "instance": 1,
            "matchnum": 34,
            "scheduled": "2025-02-27T16:50:00-05:00",
            "started": null,
            "field": "Coldspring",
            "scored": false,
            "name": "Qualifier #34",
            "alliances": [
                {
                    "color": "blue",
                    "score": 0,
                    "teams": [
                        {
                            "team": {
                                "id": 167565,
                                "name": "UND",
                                "code": null
                            },
                            "sitting": false
                        }
                    ]
                },
                {
                    "color": "red",
                    "score": 0,
                    "teams": [
                        {
                            "team": {
                                "id": 176372,
                                "name": "KGEAR",
                                "code": null
                            },
                            "sitting": false
                        }
                    ]
                }
            ],
            "updated_at": "2025-02-27T20:08:49-05:00"
        },
        {
            "id": 107549717,
            "event": {
                "id": 57770,
                "name": "SCTCC VEX U Regional Qualifying Tournament in Minnesota: VEX U Robotics Competition",
                "code": "RE-VURC-24-7770"
            },
            "division": {
                "id": 1,
                "name": "MN VEX U",
                "code": null
            },
            "round": 3,
            "instance": 3,
            "matchnum": 1,
            "scheduled": null,
            "started": "2025-02-27T18:55:19-05:00",
            "field": "UND",
            "scored": false,
            "name": "QF #3-1",
            "alliances": [
                {
                    "color": "blue",
                    "score": 4,
                    "teams": [
                        {
                            "team": {
                                "id": 167565,
                                "name": "UND",
                                "code": null
                            },
                            "sitting": false
                        }
                    ]
                },
                {
                    "color": "red",
                    "score": 38,
                    "teams": [
                        {
                            "team": {
                                "id": 63958,
                                "name": "UMN",
                                "code": null
                            },
                            "sitting": false
                        }
                    ]
                }
            ],
            "updated_at": "2025-02-27T20:08:49-05:00"
        }
    ]
}